securepasskeygen/__init__.py
securepasskeygen/generator.py
securepasskeygen-1.0.2.dist-info/LICENSE
securepasskeygen-1.0.2.dist-info/METADATA
securepasskeygen-1.0.2.dist-info/WHEEL
securepasskeygen-1.0.2.dist-info/top_level.txt
securepasskeygen-1.0.2.dist-info/RECORD
