Metadata-Version: 2.2
Name: securepasskeygen
Version: 1.0.2
Summary: A secure password generator using modern standards.
Author: Emil Holmgaard
Author-email: emil@holmgaard.io
Classifier: Programming Language :: Python :: 3
Classifier: License :: OSI Approved :: MIT License
Classifier: Operating System :: OS Independent
Requires-Python: >=3.6
License-File: LICENSE
Dynamic: author
Dynamic: author-email
Dynamic: classifier
Dynamic: description
Dynamic: description-content-type
Dynamic: requires-python
Dynamic: summary
